UrlMatch/Match.py
UrlMatch/__init__.py
UEMatch-0.1.dist-info/METADATA
UEMatch-0.1.dist-info/WHEEL
UEMatch-0.1.dist-info/top_level.txt
UEMatch-0.1.dist-info/RECORD
