Metadata-Version: 2.1
Name: UEMatch
Version: 0.1
Summary: Url and Email Match Module
Home-page: https://github.com/UniqueDevStorm/UrlMatch
Author: DevStorm
Author-email: storm@uniquecode.team
License: MIT
Platform: UNKNOWN
